{"type": "Feature", "id": 12515127, "properties": {"woe:id": 12515127, "woe:parent_id": 22660633, "woe:name": "Troms\u00f8 lufthavn Langnes", "woe:placetype": 14, "woe:placetype_name": "Airport", "woe:lang": "NOR", "iso:country": "NO", "meta:provider": ["geoplanet:7.3.1", "geoplanet:7.3.2", "geoplanet:7.4.0", "geoplanet:7.4.1", "geoplanet:7.5.1", "geoplanet:7.5.2", "geoplanet:7.6.0", "geoplanet:7.8.1", "geoplanet:7.9.0", "geoplanet:7.10.0", "geoplanet:8.0.0", "woeplanet:8.0.0"], "meta:indexed": "2020-08-20T20:57:59.291059", "woe:alias_FIN_S": ["Tromson Lentoasema"], "woe:alias_FRE_Q": ["A\u00e9roport de Troms\u00f8"], "woe:alias_FIN_Q": ["Troms\u00f6n Lentoasema"], "woe:alias_DUT_S": ["Luchthaven Tromso"], "woe:alias_DUT_Q": ["Luchthaven Troms\u00f8"], "woe:alias_GER_Q": ["Flughafen Troms\u00f8"], "meta:updated": "2020-08-22T01:58:25.327914", "woe:alias_SPA_Q": ["Aeropuerto de Troms\u00f8"], "woe:alias_FRE_S": ["Aeroport de Tromso"], "woe:alias_SPA_S": ["Aeropuerto de Tromso"], "woe:alias_POR_S": ["Aeroporto de Tromso"], "woe:alias_GER_S": ["Flughafen Tromso"], "woe:alias_POR_Q": ["Aeroporto de Troms\u00f8"], "woe:alias_ENG_V": ["Tromso Langnes", "TOS", "TOS Airport", "Tromso Airport", "Troms\u00f8 Airport"], "woe:alias_CZE_S": ["Letiste Tromso"], "woe:alias_CZE_Q": ["Letiste Troms\u00f8"], "woe:alias_ENG_P": ["Tromso Langnes Airport"], "woe:alias_NOR_S": ["Tromso Lufthavn", "Tromsoe Lufthavn", "Tromso lufthavn, Langnes", "Tromso lufthavn Langnes"], "woe:alias_SWE_Q": ["Troms\u00f6 Flygplats"], "woe:alias_UNK_Q": ["Letisko Troms\u00f8"], "woe:alias_NOR_V": ["Troms\u00f8 Lufthavn", "TOS Lufthavn", "Troms\u00f8 lufthavn, Langnes"], "woe:alias_UNK_S": ["Letisko Tromso"], "woe:alias_ITA_Q": ["Aeroporto di Troms\u00f8"], "woe:alias_ITA_S": ["Aeroporto di Tromso"], "woe:alias_SWE_S": ["Tromso Flygplats"], "woe:hierarchy": {"continent": 24865675, "country": 23424910, "town": 0, "planet": 1, "county": 12592888, "suburb": 0, "state": 2346401, "region": 0, "localadmin": 0}, "woe:timezone_id": 28350910, "woe:hash": "ukmkqhz0rhfk", "woe:centroid": [18.906401, 69.679482], "geom:latitude": 69.679482, "geom:longitude": 18.906401, "geom:hash": "ukmkqhz0rhfk", "woe:latitude": 69.679482, "geom:centroid": [18.906401, 69.679482], "woe:longitude": 18.906401, "woe:repo": "woeplanet-airport-no"}, "geometry": {"coordinates": [18.906401, 69.679482], "type": "Point"}}