{"type": "Feature", "id": 12523954, "properties": {"woe:id": 12523954, "woe:parent_id": 865411, "woe:name": "Vads\u00f8 lufthavn", "woe:placetype": 14, "woe:placetype_name": "Airport", "woe:lang": "NOR", "iso:country": "NO", "meta:provider": ["geoplanet:7.3.1", "geoplanet:7.3.2", "geoplanet:7.4.0", "geoplanet:7.4.1", "geoplanet:7.5.1", "geoplanet:7.5.2", "geoplanet:7.6.0", "geoplanet:7.8.1", "geoplanet:7.9.0", "geoplanet:7.10.0", "geoplanet:8.0.0", "woeplanet:8.0.0"], "meta:indexed": "2020-08-20T20:57:59.308245", "woe:alias_ENG_V": ["VDS Airport", "VDS"], "woe:alias_ENG_P": ["Vadso Airport"], "woe:alias_NOR_S": ["Vadso Flyplass", "Vadsoe Flyplass", "Vadso lufthavn"], "woe:alias_NOR_V": ["Vads\u00f8 Flyplass", "VDS Lufthavn"], "meta:updated": "2020-08-22T01:58:25.338872", "woe:hierarchy": {"continent": 24865675, "country": 23424910, "town": 0, "planet": 1, "county": 12592828, "suburb": 0, "state": 2346388, "region": 0, "localadmin": 0}, "woe:timezone_id": 28350910, "woe:hash": "usmnwfyb86w6", "woe:centroid": [29.83717, 70.064034], "geom:latitude": 70.064034, "geom:longitude": 29.83717, "geom:hash": "usmnwfyb86w6", "woe:latitude": 70.064034, "geom:centroid": [29.83717, 70.064034], "woe:longitude": 29.83717, "woe:repo": "woeplanet-airport-no"}, "geometry": {"coordinates": [29.83717, 70.064034], "type": "Point"}}